sayneng/__init__.py
sayneng/forecast.py
sayneng-0.1.dist-info/METADATA
sayneng-0.1.dist-info/WHEEL
sayneng-0.1.dist-info/top_level.txt
sayneng-0.1.dist-info/RECORD
