Metadata-Version: 2.1
Name: sayneng
Version: 0.1
Summary: This is a personal library.
Home-page: 
Author: wangsayneng
Author-email: sayneng69@gmail.com
Classifier: Programming Language :: Python :: 3
Classifier: License :: OSI Approved :: MIT License
Classifier: Operating System :: OS Independent
Requires-Python: >=3.7
